torch_magnus/__init__.py
torch_magnus/solvers.py
torch_magnus/utils.py
torch_magnus-0.2.0.dist-info/licenses/LICENSE
torch_magnus-0.2.0.dist-info/METADATA
torch_magnus-0.2.0.dist-info/WHEEL
torch_magnus-0.2.0.dist-info/top_level.txt
torch_magnus-0.2.0.dist-info/RECORD
