Metadata-Version: 2.4
Name: torch-magnus
Version: 0.2.0
Summary: A PyTorch-based library for batch solving homogeneous linear matrix ODEs with Magnus integrators.
Author-email: Wu-Chenyang <wuchenyang@stu.pku.edu.cn>
Project-URL: Homepage, https://github.com/Wu-Chenyang/torch_magnus
Project-URL: Bug Tracker, https://github.com/Wu-Chenyang/torch_magnus/issues
Classifier: Programming Language :: Python :: 3
Classifier: License :: OSI Approved :: MIT License
Classifier: Operating System :: OS Independent
Classifier: Intended Audience :: Science/Research
Classifier: Topic :: Scientific/Engineering :: Physics
Classifier: Topic :: Scientific/Engineering :: Mathematics
Requires-Python: >=3.8
License-File: LICENSE
Requires-Dist: torch>=1.13
Provides-Extra: dev
Requires-Dist: pytest; extra == "dev"
Requires-Dist: matplotlib; extra == "dev"
Dynamic: license-file
